MANIFEST.in
README.md
requirements.txt
setup.cfg
setup.py
versioneer.py
afctl/__init__.py
afctl/_version.py
afctl/command_line.py
afctl/exceptions.py
afctl/meta.yml
afctl/parser_helpers.py
afctl/parsers.py
afctl/utils.py
afctl.egg-info/PKG-INFO
afctl.egg-info/SOURCES.txt
afctl.egg-info/dependency_links.txt
afctl.egg-info/entry_points.txt
afctl.egg-info/requires.txt
afctl.egg-info/top_level.txt
afctl/plugins/__init__.py
afctl/plugins/deployments/__init__.py
afctl/plugins/deployments/base_deployment_config.py
afctl/plugins/deployments/deployment_config.py
afctl/plugins/deployments/deployment_config.yml
afctl/plugins/deployments/docker/__init__.py
afctl/plugins/deployments/docker/afctl_docker_compose.py
afctl/plugins/deployments/docker/deployment_config.py
afctl/plugins/deployments/qubole/__init__.py
afctl/plugins/deployments/qubole/deployment_config.py
afctl/plugins/deployments/qubole/qubole_utils.py
afctl/templates/__init__.py
afctl/templates/dag_template.py
afctl/templates/gitignore.txt