Metadata-Version: 2.1
Name: afctl
Version: 0.1.6
Summary: Python commandline tool to make deployment of Airflow projects easier.
Home-page: https://github.com/qubole/afctl
Author: Qubole
Author-email: dev@qubole.com
License: UNKNOWN
Keywords: airflow cli deployment
Platform: UNKNOWN
